{
  "model": {
    "type": "minecraft:select",
    "model": "minecraft:item/carrot_on_a_stick",
    "property": "minecraft:component",
    "component": "minecraft:lore",
    "cases": [
      {
        "when": [
          {
            "extra": [
              "animated_key"
            ],
            "text": ""
          }
        ],
        "model": {
          "type": "minecraft:model",
          "model": "fossil-frights:item/general_items/animated_key"
        }
      },
      {
        "when": [
          {
            "extra": [
              "key"
            ],
            "text": ""
          }
        ],
        "model": {
          "type": "minecraft:model",
          "model": "fossil-frights:item/general_items/key"
        }
      },
      {
        "when": [
          {
            "extra": [
              "key_cooldown"
            ],
            "text": ""
          }
        ],
        "model": {
          "type": "minecraft:model",
          "model": "fossil-frights:item/general_items/key_cooldown"
        }
      },
      {
        "when": [
          {
            "text": "Right Click - ",
            "color": "green",
            "italic": false,
            "extra": [
              {
                "text": "Restart",
                "color": "yellow",
                "italic": false
              }
            ]
          },
          {
            "text": "Drop - End",
            "color": "green",
            "italic": false
          },
          {
            "extra": [
              "parkour_restart"
            ],
            "text": ""
          }
        ],
        "model": {
          "type": "minecraft:model",
          "model": "fossil-frights:item/general_items/parkour_restart"
        }
      },
      {
        "when": [
          {
            "text": "Right Click - ",
            "color": "green",
            "italic": false,
            "extra": [
              {
                "text": "Restart",
                "color": "yellow",
                "italic": false
              }
            ]
          },
          {
            "text": "Drop - End",
            "color": "green",
            "italic": false
          },
          {
            "extra": [
              "temple_run_restart"
            ],
            "text": ""
          }
        ],
        "model": {
          "type": "minecraft:model",
          "model": "fossil-frights:item/general_items/temple_run_restart"
        }
      },
      {
        "when": [
          {
            "extra": [
              "parkour_restart"
            ],
            "text": ""
          }
        ],
        "model": {
          "type": "minecraft:model",
          "model": "fossil-frights:item/general_items/parkour_restart"
        }
      },
      {
        "when": [
          {
            "extra": [
              "temple_run_restart"
            ],
            "text": ""
          }
        ],
        "model": {
          "type": "minecraft:model",
          "model": "fossil-frights:item/general_items/temple_run_restart"
        }
      },
      {
        "when": [
          {
            "extra": [
              "key_disabled"
            ],
            "text": ""
          }
        ],
        "model": {
          "type": "minecraft:model",
          "model": "fossil-frights:item/general_items/key_disabled"
        }
      }
    ],
    "fallback": {
      "type": "minecraft:model",
      "model": "minecraft:item/carrot_on_a_stick"
    }
  }
}
